async_nec_beamer/__init__.py
async_nec_beamer/nec_beamer.py
async_nec_beamer-0.2.2.data/scripts/async_nec_beamer
async_nec_beamer-0.2.2.dist-info/LICENSE
async_nec_beamer-0.2.2.dist-info/METADATA
async_nec_beamer-0.2.2.dist-info/WHEEL
async_nec_beamer-0.2.2.dist-info/top_level.txt
async_nec_beamer-0.2.2.dist-info/RECORD
