Metadata-Version: 2.1
Name: async-nec-beamer
Version: 0.2.2
Summary: NEC Beamer Web Interface Wrapper (Async)
Home-page: https://github.com/heinrich-foto/async_nec_beamer
Author: Heinrich-Foto
Author-email: async_nec_beamer@heinrich-foto.de
License: MIT
License-File: LICENSE
Requires-Dist: aiohttp[speedups]
Requires-Dist: click
